loma/__init__.py
loma-0.0.2.dist-info/METADATA
loma-0.0.2.dist-info/WHEEL
loma-0.0.2.dist-info/top_level.txt
loma-0.0.2.dist-info/RECORD
