Metadata-Version: 2.4
Name: loma
Version: 0.0.2
Summary: loma.
Author-email: Caden Chen <cadenc.woss@gmail.com>
License: MIT
Classifier: Programming Language :: Python :: 3
Classifier: License :: OSI Approved :: MIT License
Requires-Python: >=3.7
